word_document_typeset/__init__.py
word_document_typeset/main.py
word_document_typeset/tools.py
word_document_typeset/utils.py
word_document_typeset-1.0.3.dist-info/METADATA
word_document_typeset-1.0.3.dist-info/WHEEL
word_document_typeset-1.0.3.dist-info/entry_points.txt
word_document_typeset-1.0.3.dist-info/top_level.txt
word_document_typeset-1.0.3.dist-info/RECORD
